openapi_service_client/__init__.py
openapi_service_client/client.py
openapi_service_client/client_configuration.py
openapi_service_client/config/__init__.py
openapi_service_client/config/auth_strategy.py
openapi_service_client/config/configuration.py
openapi_service_client/http_client/__init__.py
openapi_service_client/http_client/client.py
openapi_service_client/providers/__init__.py
openapi_service_client/providers/anthropic.py
openapi_service_client/providers/cohere.py
openapi_service_client/providers/converter.py
openapi_service_client/providers/llm_provider.py
openapi_service_client/providers/openai.py
openapi_service_client/providers/payload_extractor.py
openapi_service_client/request_builder/__init__.py
openapi_service_client/request_builder/builder.py
openapi_service_client/spec/__init__.py
openapi_service_client/spec/open_api_spec.py
openapi_service_client/spec/operation.py
openapi_service_client-0.0.10.dist-info/METADATA
openapi_service_client-0.0.10.dist-info/WHEEL
openapi_service_client-0.0.10.dist-info/licenses/LICENSE
openapi_service_client-0.0.10.dist-info/RECORD
