Metadata-Version: 2.3
Name: openapi-service-client
Version: 0.0.10
Summary: A client library for invoking APIs based on provided OpenAPI specifications
Project-URL: Documentation, https://github.com/vblagoje/openapi-service-client/blob/main/README.md
Project-URL: Issues, https://github.com/vblagoje/openapi-service-client/issues
Project-URL: Source, https://github.com/vblagoje/openapi-service-client
Author-email: Vladimir Blagojevic <dovlex@gmail.com>
License-Expression: Apache-2.0
License-File: LICENSE
Classifier: Development Status :: 4 - Beta
Classifier: Programming Language :: Python
Classifier: Programming Language :: Python :: 3.9
Classifier: Programming Language :: Python :: 3.10
Classifier: Programming Language :: Python :: 3.11
Classifier: Programming Language :: Python :: Implementation :: PyPy
Requires-Python: >=3.8
Requires-Dist: jsonref
Requires-Dist: pyyaml
Requires-Dist: requests
